README.md
setup.py
feathery/__init__.py
feathery/client.py
feathery/constants.py
feathery/polling.py
feathery/rwlock.py
feathery/utils.py
feathery_server_sdk.egg-info/PKG-INFO
feathery_server_sdk.egg-info/SOURCES.txt
feathery_server_sdk.egg-info/dependency_links.txt
feathery_server_sdk.egg-info/top_level.txt
tests/__init__.py
tests/constants.py
tests/test_client.py
tests/test_polling.py